Metadata-Version: 2.1
Name: pythonbotcreator
Version: 0.1
Summary: Telegram Bots and Automation of tasks.
Author-email: contact@pythonbotcreator.in
